unitree_dds_wrapper/__init__.py
unitree_dds_wrapper/client.py
unitree_dds_wrapper/dds_context.py
unitree_dds_wrapper/publisher.py
unitree_dds_wrapper/server.py
unitree_dds_wrapper/subscription.py
unitree_dds_wrapper/idl/__init__.py
unitree_dds_wrapper/idl/builtin_interfaces/__init__.py
unitree_dds_wrapper/idl/builtin_interfaces/msg/__init__.py
unitree_dds_wrapper/idl/builtin_interfaces/msg/dds_/_Duration_.py
unitree_dds_wrapper/idl/builtin_interfaces/msg/dds_/_Time_.py
unitree_dds_wrapper/idl/builtin_interfaces/msg/dds_/__init__.py
unitree_dds_wrapper/idl/geometry_msgs/__init__.py
unitree_dds_wrapper/idl/geometry_msgs/msg/__init__.py
unitree_dds_wrapper/idl/geometry_msgs/msg/dds_/_Point32_.py
unitree_dds_wrapper/idl/geometry_msgs/msg/dds_/_PointStamped_.py
unitree_dds_wrapper/idl/geometry_msgs/msg/dds_/_Point_.py
unitree_dds_wrapper/idl/geometry_msgs/msg/dds_/_Pose2D_.py
unitree_dds_wrapper/idl/geometry_msgs/msg/dds_/_PoseStamped_.py
unitree_dds_wrapper/idl/geometry_msgs/msg/dds_/_PoseWithCovarianceStamped_.py
unitree_dds_wrapper/idl/geometry_msgs/msg/dds_/_PoseWithCovariance_.py
unitree_dds_wrapper/idl/geometry_msgs/msg/dds_/_Pose_.py
unitree_dds_wrapper/idl/geometry_msgs/msg/dds_/_QuaternionStamped_.py
unitree_dds_wrapper/idl/geometry_msgs/msg/dds_/_Quaternion_.py
unitree_dds_wrapper/idl/geometry_msgs/msg/dds_/_TransformStamped_.py
unitree_dds_wrapper/idl/geometry_msgs/msg/dds_/_Transform_.py
unitree_dds_wrapper/idl/geometry_msgs/msg/dds_/_TwistStamped_.py
unitree_dds_wrapper/idl/geometry_msgs/msg/dds_/_TwistWithCovarianceStamped_.py
unitree_dds_wrapper/idl/geometry_msgs/msg/dds_/_TwistWithCovariance_.py
unitree_dds_wrapper/idl/geometry_msgs/msg/dds_/_Twist_.py
unitree_dds_wrapper/idl/geometry_msgs/msg/dds_/_Vector3_.py
unitree_dds_wrapper/idl/geometry_msgs/msg/dds_/__init__.py
unitree_dds_wrapper/idl/nav_msgs/__init__.py
unitree_dds_wrapper/idl/nav_msgs/msg/__init__.py
unitree_dds_wrapper/idl/nav_msgs/msg/dds_/_MapMetaData_.py
unitree_dds_wrapper-2.0.7.dist-info/METADATA
unitree_dds_wrapper-2.0.7.dist-info/WHEEL
unitree_dds_wrapper-2.0.7.dist-info/top_level.txt
unitree_dds_wrapper-2.0.7.dist-info/RECORD
