Metadata-Version: 2.4
Name: unitree_dds_wrapper
Version: 2.0.7
Summary: Unitree DDS Wrapper to simplify the communication with Unitree Robots
Author-email: Agnel Wang <2273421791wk@gmail.com>
License: Apache License 2.0
Classifier: Programming Language :: Python :: 3
Classifier: License :: OSI Approved :: Apache Software License
Classifier: Operating System :: OS Independent
Requires-Dist: cyclonedds
Requires-Dist: pygame
Requires-Dist: numpy
